puring/__init__.py
puring/actions.py
puring/index.py
puring/struct.py
puring/utils.py
pyturing/__init__.py
pyturing/actions.py
pyturing/index.py
pyturing/utils.py
turing/__init__.py
turing/actions.py
turing/index.py
turing/utils.py
puring-0.1.4.dist-info/METADATA
puring-0.1.4.dist-info/WHEEL
puring-0.1.4.dist-info/top_level.txt
puring-0.1.4.dist-info/RECORD
