Metadata-Version: 2.4
Name: puring
Version: 0.1.4
Summary: Object-oriented Turing machine emulator
Home-page: https://github.com/mctood/puring
Author: rogatka
Author-email: petfert405@gmail.com
Classifier: Programming Language :: Python :: 3
Classifier: License :: OSI Approved :: MIT License
Requires-Python: >=3.7
Dynamic: author
Dynamic: author-email
Dynamic: classifier
Dynamic: description
Dynamic: description-content-type
Dynamic: home-page
Dynamic: requires-python
Dynamic: summary
